canonical_transformer/__init__.py
canonical_transformer/alias_functions.py
canonical_transformer/dataframe_utils.py
canonical_transformer/format_utils.py
canonical_transformer/loader_utils.py
canonical_transformer/mapping_utils.py
canonical_transformer/path_director.py
canonical_transformer/save_utils.py
canonical_transformer/specialized_utils.py
canonical_transformer/xml_utils.py
canonical_transformer/deprecated-version027/__init__.py
canonical_transformer/deprecated-version027/alias_functions.py
canonical_transformer/deprecated-version027/dataframe_utils.py
canonical_transformer/deprecated-version027/format_utils.py
canonical_transformer/deprecated-version027/loader_utils.py
canonical_transformer/deprecated-version027/mapping_utils.py
canonical_transformer/deprecated-version027/save_utils.py
canonical_transformer/deprecated-version027/specialized_utils.py
canonical_transformer/deprecated-version027/xml_utils.py
canonical_transformer/format_transformer/__init__.py
canonical_transformer/format_transformer/number_format.py
canonical_transformer/functionals/__init__.py
canonical_transformer/functionals/basis.py
canonical_transformer/isomorphisms/__init__.py
canonical_transformer/isomorphisms/basis.py
canonical_transformer/isomorphisms/id_df.py
canonical_transformer/matrix_representation/__init__.py
canonical_transformer/matrix_representation/matrix.py
canonical_transformer/matrix_representation/matrix_utils.py
canonical_transformer/morphisms/__init__.py
canonical_transformer/morphisms/basis.py
canonical_transformer/morphisms/map_csv.py
canonical_transformer/morphisms/map_data.py
canonical_transformer/morphisms/map_db.py
canonical_transformer/morphisms/map_df.py
canonical_transformer/morphisms/map_json.py
canonical_transformer/morphisms/map_s3.py
canonical_transformer/morphisms/map_srs.py
canonical_transformer/tests/__init__.py
canonical_transformer/tests/test_isomorphism.py
canonical_transformer-1.0.8.dist-info/METADATA
canonical_transformer-1.0.8.dist-info/WHEEL
canonical_transformer-1.0.8.dist-info/top_level.txt
canonical_transformer-1.0.8.dist-info/RECORD
