Metadata-Version: 2.4
Name: canonical_transformer
Version: 1.0.8
Summary: A Python module for preserving structural isomorphisms across data transformations, ensuring reversible and type-stable conversions between formats like DataFrame, JSON, and dict.
Home-page: https://github.com/nailen1/canonical_transformer.git
Author: June Young Park
Author-email: juneyoungpaak@gmail.com
Classifier: Programming Language :: Python :: 3
Classifier: License :: OSI Approved :: MIT License
Classifier: Operating System :: OS Independent
Classifier: Development Status :: 5 - Production/Stable
Classifier: Intended Audience :: Developers
Classifier: Intended Audience :: Science/Research
Classifier: Topic :: Scientific/Engineering :: Information Analysis
Classifier: Topic :: Software Development :: Libraries :: Python Modules
Requires-Python: >=3.6
Requires-Dist: numpy>=2.1.3
Requires-Dist: pandas>=2.2.3
Requires-Dist: python-dateutil>=2.9.0
Requires-Dist: pytz>=2024.2
Requires-Dist: typing_extensions>=4.12.2
Requires-Dist: deepdiff>=8.5.0
Dynamic: author
Dynamic: author-email
Dynamic: classifier
Dynamic: description
Dynamic: description-content-type
Dynamic: home-page
Dynamic: requires-dist
Dynamic: requires-python
Dynamic: summary
